index_importer/__init__.py
index_importer/main.py
beaver_index_importer-0.1.2.dist-info/METADATA
beaver_index_importer-0.1.2.dist-info/WHEEL
beaver_index_importer-0.1.2.dist-info/entry_points.txt
beaver_index_importer-0.1.2.dist-info/licenses/LICENSE
beaver_index_importer-0.1.2.dist-info/RECORD
