Metadata-Version: 2.4
Name: beaver-index-importer
Version: 0.1.2
Summary: A CLI tool to import siglip2 image  index files (.jsonl, .pkl) into a BeaverDB.
Project-URL: Homepage, https://github.com/yudivian/beaver-index-importer
Project-URL: Issues, https://github.com/yudivian/beaver-index-importer/issues
Author-email: Yudivián Almeida Cruz <yudivian@gmail.com>
License-Expression: MIT
License-File: LICENSE
Classifier: License :: OSI Approved :: MIT License
Classifier: Operating System :: OS Independent
Classifier: Programming Language :: Python :: 3
Requires-Python: >=3.13
Requires-Dist: beaver-db[full]
Requires-Dist: pyyaml>=6.0
Requires-Dist: tqdm>=4.60.0
